google_text_to_speech/__init__.py
google_text_to_speech/_version.py
google_text_to_speech/google_translate_tts.py
google_text_to_speech-0.1.27.dist-info/LICENSE
google_text_to_speech-0.1.27.dist-info/METADATA
google_text_to_speech-0.1.27.dist-info/WHEEL
google_text_to_speech-0.1.27.dist-info/top_level.txt
google_text_to_speech-0.1.27.dist-info/RECORD
