Metadata-Version: 2.1
Name: google-text-to-speech
Version: 0.1.27
Summary: A text-to-speech conversion tool using Google Translate API
Home-page: https://gitlab.com/labsoft-ai/google-translate-tts
Author: Momcilo Krunic
Author-email: momcilo.krunic@labsoft.ai
License: MIT
Platform: UNKNOWN
Classifier: Programming Language :: Python :: 3
Classifier: License :: OSI Approved :: MIT License
Classifier: Operating System :: OS Independent
License-File: LICENSE
Requires-Dist: requests
Requires-Dist: playsound
